{
  "sections": [
    {
      "heading": "Overview",
      "content": "Neuroblastoma is a cancer that originates from the developing sympathetic nervous system and is the most common extracranial solid tumor in children [1,2]. Due to the heterogenous nature of neuroblastoma—with some patients experiencing spontaneous regression and others requiring intensive multimodal therapy—a risk-adapted, multidisciplinary approach is essential. Approximately 600 to 800 patients are diagnosed annually in the United States, with an average age at diagnosis of 1 to 2 years, and the vast majority are <5 years of age [3,4]. Treatment is stratified by risk group (low, intermediate, or high) based on the International Neuroblastoma Risk Group (INRG) Risk Classification System, which incorporates age at diagnosis, INRG stage, MYCN amplification status, histopathology, segmental chromosomal aberrations (SCA), and DNA index (DI) [47]. The goal of therapy for low- and intermediate-risk patients is to cure disease with minimal toxicity, while high-risk patients require intensive multimodal therapy divided into induction, consolidation, and post-consolidation phases [MS-10]. The NCCN Neuroblastoma Panel recommends participation in clinical trials when available and applicable [NEUROB-D 3 of 13]."
    }
  ],
  "flowchart": {
    "nodes": [
      {
        "id": "n1",
        "label": "Neuroblastoma Diagnosis",
        "type": "decision"
      },
      {
        "id": "n2",
        "label": "Risk Stratification (INRG)",
        "type": "decision"
      },
      {
        "id": "n3",
        "label": "Low-Risk",
        "type": "outcome"
      },
      {
        "id": "n4",
        "label": "Intermediate-Risk",
        "type": "outcome"
      },
      {
        "id": "n5",
        "label": "High-Risk",
        "type": "outcome"
      },
      {
        "id": "n6",
        "label": "Relapsed/Refractory",
        "type": "outcome"
      },
      {
        "id": "n7",
        "label": "Observation or Surgical Resection",
        "type": "treatment"
      },
      {
        "id": "n8",
        "label": "Moderate Chemotherapy + Surgery",
        "type": "treatment"
      },
      {
        "id": "n9",
        "label": "Intensive Multimodal Therapy (Induction→Consolidation→Post-Consolidation)",
        "type": "treatment"
      },
      {
        "id": "n10",
        "label": "Individualized Therapy (Chemoimmunotherapy, MIBG, targeted agents, etc.)",
        "type": "treatment"
      }
    ],
    "edges": [
      {
        "source": "n1",
        "target": "n2",
        "label": "Pathological diagnosis confirmed"
      },
      {
        "source": "n2",
        "target": "n3",
        "label": "Low-risk"
      },
      {
        "source": "n2",
        "target": "n4",
        "label": "Intermediate-risk"
      },
      {
        "source": "n2",
        "target": "n5",
        "label": "High-risk"
      },
      {
        "source": "n2",
        "target": "n6",
        "label": "Relapsed/Refractory"
      },
      {
        "source": "n3",
        "target": "n7",
        "label": "Treatment"
      },
      {
        "source": "n4",
        "target": "n8",
        "label": "Treatment"
      },
      {
        "source": "n5",
        "target": "n9",
        "label": "Treatment"
      },
      {
        "source": "n6",
        "target": "n10",
        "label": "Treatment"
      }
    ]
  },
  "cards": [
    {
      "title": "Curative",
      "detail": "Surgical resection or observation with surveillance, depending on INRG stage and biologic features [NEUROB-3]. For patients with L1 tumors, surgery is often curative. Infants <6 months with L1 adrenal tumors ≤3.1 cm solid or ≤5 cm cystic may be observed without biopsy [NEUROB-3, NEUROB-D 1 of 13].",
      "color": "#10b981"
    },
    {
      "title": "Curative",
      "detail": "Combined moderate-intensity multiagent chemotherapy (2–8 cycles based on risk factors) and surgical resection, with treatment tailored to disease biology and response [NEUROB-4–6, NEUROB-D 1 of 13].",
      "color": "#10b981"
    },
    {
      "title": "Curative",
      "detail": "Intensive multimodal therapy including induction chemotherapy, surgical resection, high-dose chemotherapy with autologous stem cell rescue (tandem transplant recommended for most patients, category 1), consolidative radiation therapy, post-consolidation anti-GD2 immunotherapy with isotretinoin, and optional continuation therapy with eflornithine [NEUROB-7–11, NEUROB-D 3 of 13].",
      "color": "#10b981"
    },
    {
      "title": "Disease control / palliative",
      "detail": "Individualized therapy including chemoimmunotherapy (anti-GD2 antibody with chemotherapy), I-131 MIBG, targeted agents for actionable alterations (e.g., ALK inhibitors), radiation, surgery, or clinical trials [NEUROB-D 10 of 13].",
      "color": "#10b981"
    }
  ],
  "_section": "management_principles",
  "_site_id": "neuroblastoma",
  "_chars_in": 4341
}