{
  "title": "Mixed Methods Trajectory Analysis of Daily Educational and Social Experiences of Youth With Cancer From Diagnosis to Early Survivorship.",
  "pmid": "42470244",
  "abstract": "Youth with cancer may face acute and long-term academic and social challenges. Most existing research has relied on cross-sectional or single-informant methods to describe these challenges. This longitudinal, convergent mixed-methods study aimed to characterize academic and social challenges faced by youth with cancer, from the perspective of youth, caregivers, and educators-from onset of diagnosis into survivorship.",
  "journal": "Psychooncology",
  "year": "2026",
  "authors": [
    "Moscato EL",
    "Duan Q",
    "Hammad S",
    "Siddiqui MA",
    "Stabl I"
  ],
  "doi": "10.1002/pon.70543",
  "query_date": "2026-07-19T17:33:15.801058",
  "trial_name": "AFFIRM"
}