{
  "pmid": "41788456",
  "title": "First-Line Serplulimab versus Other Anti-PD-1/PD-L1 Antibodies Plus Chemotherapy for Esophageal Squamous Cell Carcinoma: A Systematic Review with Benefit-Risk Assessment via Matching-Adjusted Indirect Comparison.",
  "abstract": "Blockade of the PD-L1/PD-1 pathway combined with chemotherapy has demonstrated significant survival benefits as first&#x2011;line therapy for esophageal squamous cell carcinoma (ESCC). However, comprehensive benefit-risk comparisons among approved agents remain limited. This study conducted an indirect comparison of serplulimab versus other anti-PD-1/PD-L1 antibodies plus chemotherapy in treatment-na&#xef;ve ESCC patients.",
  "journal": "Biologics",
  "year": "2026",
  "authors": [
    "Zhu Y",
    "Qi X",
    "Ni S",
    "Qiu W",
    "Chen M"
  ],
  "doi": "10.2147/BTT.S602654",
  "query_date": "2026-07-18T20:41:12.168616",
  "trial_name": "CheckMate-648"
}