{
  "title": "Case Report: Trazodone as a possible treatment for psychiatric adverse events related to ALK inhibitors.",
  "pmid": "42454327",
  "abstract": "Lorlatinib is a third-generation tyrosine kinase inhibitor approved for the first-line treatment of ALK-positive metastatic non-small cell lung cancer, frequently associated with psychiatric adverse events.",
  "journal": "Front Psychiatry",
  "year": "2026",
  "authors": [
    "Persico L",
    "Miuli A",
    "Chiappini S",
    "Mosca A",
    "De Tursi M"
  ],
  "doi": "10.3389/fpsyt.2026.1718767",
  "query_date": "2026-07-19T16:53:15.492826",
  "trial_name": "First-line lorlatinib or crizotinib in advanced ALK-positive lung cancer"
}