{
  "pmid": "32090636",
  "title": "Health-related quality of life results from the IFM 2009 trial: treatment with lenalidomide, bortezomib, and dexamethasone in transplant-eligible patients with newly diagnosed multiple myeloma.",
  "abstract": "The Intergroupe Francophone du Myelome 2009 trial (NCT01191060) assessed health-related quality of life (HRQoL) in patients with newly diagnosed multiple myeloma (NDMM) receiving lenalidomide/bortezomib/dexamethasone (RVd) induction therapy followed by consolidation therapy with either autologous stem cell transplantation (ASCT) plus RVd (RVd-ASCT) or RVd-alone; both groups then received lenalidomide maintenance therapy for 1&#x2009;year. Global HRQoL, physical functioning, and role functioning scores significantly improved for both cohorts from baseline to the end of consolidation and were sustained during maintenance and follow-up, with clinically meaningful changes (RVd-alone: p &#x2009;=&#x2009;.0002; RVd-ASCT: p &#x2009;&lt;&#x2009;.001). Similarly, both groups showed clinically meaningful improvements from baseline in fatigue, pain, and disease symptom scores. Side effects of treatment scores remained stable. In the RVd-ASCT group, there was transient worsening in HRQoL immediately after ASCT. These findings suggest that the clinical improvements observed with RVd-based treatment are accompanied by overall improvements in HRQoL for patients with NDMM.",
  "journal": "Leuk Lymphoma",
  "year": "2020",
  "authors": [
    "Roussel M",
    "Hebraud B",
    "Hulin C",
    "Perrot A",
    "Caillot D"
  ],
  "doi": "10.1080/10428194.2020.1719091",
  "query_date": "2026-07-18T20:48:25.064078",
  "trial_name": "IFM 2009"
}