{
  "title": "Case Report: Dramatic response to amivantamab plus chemotherapy in EGFR G719A-mutant lung adenocarcinoma with liver and peritoneal metastases.",
  "pmid": "42272656",
  "abstract": "Hepatic metastasis and uncommon mutations are recognized risk factors in patients with epidermal growth factor receptor (EGFR)-mutant non-small cell lung cancer. The phase 3 MARIPOSA-2 trial demonstrated superior outcomes with amivantamab plus chemotherapy compared to chemotherapy alone in patients whose disease progressed during EGFR-tyrosine kinase inhibitor therapy. However, its efficacy and tolerability in patients with hepatic metastases or uncommon EGFR mutations remain unclear.",
  "journal": "Front Oncol",
  "year": "2026",
  "authors": [
    "Kim J",
    "Kim HG",
    "Lee SH"
  ],
  "doi": "10.3389/fonc.2026.1820018",
  "query_date": "2026-07-19T17:13:33.421376",
  "trial_name": "Pemetrexed-carboplatin salvage therapy"
}