{
  "pmid": "41746630",
  "title": "First-Line Tislelizumab Plus Chemotherapy for Recurrent or Metastatic Nasopharyngeal Cancer: Three-Year Follow-Up of the Phase 3 RATIONALE-309 Randomized Clinical Trial.",
  "abstract": "Nasopharyngeal carcinoma (NPC) is a major health concern in Asia, and treatment options for recurrent or metastatic disease are limited. Immunotherapy plus chemotherapy has shown promise, but long-term data are needed to guide first-line treatment.",
  "journal": "JAMA Oncol",
  "year": "2026",
  "authors": [
    "Yang Y",
    "Yen CJ",
    "Pan J",
    "Wang H",
    "Qu S"
  ],
  "doi": "10.1001/jamaoncol.2026.0020",
  "query_date": "2026-07-18T21:02:56.544637",
  "trial_name": "RATIONALE-309"
}