{
  "title": "Management of pediatric bone sarcomas.",
  "pmid": "41363185",
  "abstract": "Pediatric bone sarcomas - principally osteosarcoma (OS) and Ewing sarcoma (ES) - remain curable for many with localized disease, but outcomes for metastatic or relapsed cases have stagnated. We synthesize recent clinically relevant developments that inform diagnosis, risk stratification, local control, systemic therapy, and survivorship in children and adolescents.",
  "journal": "Curr Opin Pediatr",
  "year": "2026",
  "authors": [
    "Elliott L",
    "Loeb DM",
    "Trucco M"
  ],
  "doi": "10.1097/MOP.0000000000001535",
  "query_date": "2026-07-19T17:30:41.646307",
  "trial_name": "rEECur"
}