{
  "title": "Efficacy of nivolumab plus relatlimab versus BRAF/MEK inhibitors for first-line treatment of BRAF-mutant advanced melanoma: A matching-adjusted indirect comparison.",
  "pmid": "41971757",
  "abstract": "Dual immuno-oncology (IO) therapy or BRAF/MEK inhibitor combinations are approved first-line (1L) treatment options for BRAF- mutant advanced melanoma. In the absence of head-to-head trials comparing 1L nivolumab plus relatlimab (NIVO+RELA) to BRAF/MEK inhibitors, we compared its efficacy to dabrafenib+trametinib (DAB+TRAM), encorafenib+binimetinib (ENCO+BINI), vemurafenib+cobimetinib (VEM+COBI) and atezolizumab (ATEZO)+VEM+COBI using matching-adjusted indirect comparisons (MAICs).",
  "journal": "BMJ Oncol",
  "year": "2025",
  "authors": [
    "Miller DM",
    "Smithy JW",
    "Palaia J",
    "Patel D",
    "Salvatore A"
  ],
  "doi": "10.1136/bmjonc-2025-000912",
  "query_date": "2026-07-19T17:19:43.642823",
  "trial_name": "RELATIVITY-047"
}