{
  "nct_id": "NCT05798897",
  "brief_title": "Safety and Preliminary Efficacy of MT-601 in Patients With Relapsed/Refractory Lymphoma",
  "official_title": "A Phase 1 Study of Patient-Derived Multi-Tumor-Associated Antigen-Specific T Cells (MT-601) Administered to Patients With Relapsed or Refractory Non-Hodgkin and Hodgkin Lymphoma (APOLLO)",
  "phase": [
    "PHASE1"
  ],
  "enrollment": 79,
  "status": "RECRUITING",
  "has_results": false,
  "pmids": [],
  "outcomes": [],
  "acronym": "APOLLO",
  "site_id": "myeloma",
  "query_date": "2026-07-19T15:51:06.771618",
  "trial_name": "APOLLO"
}